[{"id": "10195669429", "type": "CreateEvent", "actor": {"id": 107138522, "login": "ANCIENTINSANE", "display_login": "ANCIENTINSANE", "gravatar_id": "", "url": "https://api.github.com/users/ANCIENTINSANE", "avatar_url": "https://avatars.githubusercontent.com/u/107138522?", "location": "India"}, "repo": {"id": 1185190106, "name": "ANCIENTINSANE/Fairlx-Dev", "url": "https://api.github.com/repos/ANCIENTINSANE/Fairlx-Dev"}, "payload": {"ref": "dev", "ref_type": "branch", "full_ref": "refs/heads/dev", "master_branch": "main", "description": "Fairlx is an open-source, AI-powered, enterprise-ready project management platform that combines fair usage billing, modern workflows, and scalable architecture for growing organizations.", "pusher_type": "user"}, "public": true, "created_at": "2026-04-04T19:42:36Z"}, {"id": "10195669424", "type": "PushEvent", "actor": {"id": 41898282, "login": "github-actions[bot]", "display_login": "github-actions", "gravatar_id": "", "url": "https://api.github.com/users/github-actions[bot]", "avatar_url": "https://avatars.githubusercontent.com/u/41898282?", "location": "Not Specified"}, "repo": {"id": 920701581, "name": "cbs-news-data/air-quality-med-unit", "url": "https://api.github.com/repos/cbs-news-data/air-quality-med-unit"}, "payload": {"repository_id": 920701581, "push_id": 32488771602, "ref": "refs/heads/main", "head": "89adbf245a68ff32df20915e10347d8da084bb59", "before": "211e1d52028f5dc79dd3c914d6e03656300d230a"}, "public": true, "created_at": "2026-04-04T19:42:36Z", "org": {"id": 107130607, "login": "cbs-news-data", "gravatar_id": "", "url": "https://api.github.com/orgs/cbs-news-data", "avatar_url": "https://avatars.githubusercontent.com/u/107130607?"}}, {"id": "10195669376", "type": "PushEvent", "actor": {"id": 269720916, "login": "fidannaslanova", "display_login": "fidannaslanova", "gravatar_id": "", "url": "https://api.github.com/users/fidannaslanova", "avatar_url": "https://avatars.githubusercontent.com/u/269720916?", "location": "Not Specified"}, "repo": {"id": 1195154288, "name": "fidannaslanova/holbertonschool-shell", "url": "https://api.github.com/repos/fidannaslanova/holbertonschool-shell"}, "payload": {"repository_id": 1195154288, "push_id": 32488771538, "ref": "refs/heads/main", "head": "dca92129f75e662f5a6624bccc13e5cad6edc9af", "before": "6ba7903b69253242ebb70688e9040f87f0046849"}, "public": true, "created_at": "2026-04-04T19:42:36Z"}, {"id": "10195669382", "type": "PushEvent", "actor": {"id": 41898282, "login": "github-actions[bot]", "display_login": "github-actions", "gravatar_id": "", "url": "https://api.github.com/users/github-actions[bot]", "avatar_url": "https://avatars.githubusercontent.com/u/41898282?", "location": "Not Specified"}, "repo": {"id": 1194785120, "name": "ox30/tomtom_monitoring_a13-a2", "url": "https://api.github.com/repos/ox30/tomtom_monitoring_a13-a2"}, "payload": {"repository_id": 1194785120, "push_id": 32488771552, "ref": "refs/heads/captures", "head": "f57877b4261a2b8d9644ac3f61d801f012285074", "before": "dfd3652c36cac34e44c55a326ffa96a54068ca24"}, "public": true, "created_at": "2026-04-04T19:42:36Z"}, {"id": "10195669386", "type": "PushEvent", "actor": {"id": 146426659, "login": "AmirhosseinIranmehr", "display_login": "AmirhosseinIranmehr", "gravatar_id": "", "url": "https://api.github.com/users/AmirhosseinIranmehr", "avatar_url": "https://avatars.githubusercontent.com/u/146426659?", "location": "Edmonton, Alberta, Canada"}, "repo": {"id": 1195701265, "name": "AmirhosseinIranmehr/AmirhosseinIranmehr.github.io", "url": "https://api.github.com/repos/AmirhosseinIranmehr/AmirhosseinIranmehr.github.io"}, "payload": {"repository_id": 1195701265, "push_id": 32488771553, "ref": "refs/heads/main", "head": "033f6efccb9aa84ce3bcb67de772ab68651447f8", "before": "bb9654e6d811e5870b6aa43332eaa5946e1b55f2"}, "public": true, "created_at": "2026-04-04T19:42:36Z"}, {"id": "10195669390", "type": "DeleteEvent", "actor": {"id": 192509972, "login": "cola500", "display_login": "cola500", "gravatar_id": "", "url": "https://api.github.com/users/cola500", "avatar_url": "https://avatars.githubusercontent.com/u/192509972?", "location": "Not Specified"}, "repo": {"id": 1094377460, "name": "cola500/equinet", "url": "https://api.github.com/repos/cola500/equinet"}, "payload": {"ref": "feature/s16-2-seed-supabase-auth", "ref_type": "branch", "full_ref": "refs/heads/feature/s16-2-seed-supabase-auth", "pusher_type": "user"}, "public": true, "created_at": "2026-04-04T19:42:36Z"}, {"id": "10195669395", "type": "PushEvent", "actor": {"id": 40501032, "login": "deadly009", "display_login": "deadly009", "gravatar_id": "", "url": "https://api.github.com/users/deadly009", "avatar_url": "https://avatars.githubusercontent.com/u/40501032?", "location": "Egypt"}, "repo": {"id": 946489229, "name": "deadly009/gg", "url": "https://api.github.com/repos/deadly009/gg"}, "payload": {"repository_id": 946489229, "push_id": 32488771554, "ref": "refs/heads/main", "head": "4a44f42c04b5b32e0246a910ca424c543d0f9a7d", "before": "eb5e3dbee48b8d72bb0fabd4c4ac31a5048d2fec"}, "public": true, "created_at": "2026-04-04T19:42:36Z"}, {"id": "10195669399", "type": "PushEvent", "actor": {"id": 41898282, "login": "github-actions[bot]", "display_login": "github-actions", "gravatar_id": "", "url": "https://api.github.com/users/github-actions[bot]", "avatar_url": "https://avatars.githubusercontent.com/u/41898282?", "location": "Not Specified"}, "repo": {"id": 1016605011, "name": "kalimbgn12/fan", "url": "https://api.github.com/repos/kalimbgn12/fan"}, "payload": {"repository_id": 1016605011, "push_id": 32488771560, "ref": "refs/heads/master", "head": "88e8785204ef308cdd236f5655dd1bb238371546", "before": "c28b46e657b77747a56f1c42b9ce10dc1b245080"}, "public": true, "created_at": "2026-04-04T19:42:36Z"}, {"id": "10195669400", "type": "PushEvent", "actor": {"id": 74459478, "login": "harkerhand", "display_login": "harkerhand", "gravatar_id": "", "url": "https://api.github.com/users/harkerhand", "avatar_url": "https://avatars.githubusercontent.com/u/74459478?", "location": "Nanjing, China"}, "repo": {"id": 1199399952, "name": "harkerhand/MiniCode-rs", "url": "https://api.github.com/repos/harkerhand/MiniCode-rs"}, "payload": {"repository_id": 1199399952, "push_id": 32488771570, "ref": "refs/heads/master", "head": "f7fe909a6c9c4f85204c5695f30cba0440be780a", "before": "f17c53580cbbd7f8c9f7e0bf1cc2642109440fa9"}, "public": true, "created_at": "2026-04-04T19:42:36Z"}, {"id": "10195669401", "type": "PushEvent", "actor": {"id": 48622694, "login": "devorous", "display_login": "devorous", "gravatar_id": "", "url": "https://api.github.com/users/devorous", "avatar_url": "https://avatars.githubusercontent.com/u/48622694?", "location": "Not Specified"}, "repo": {"id": 1132478691, "name": "devorous/top-draw", "url": "https://api.github.com/repos/devorous/top-draw"}, "payload": {"repository_id": 1132478691, "push_id": 32488771579, "ref": "refs/heads/main", "head": "4e318fc7ab57a5df650158fd3a085bfd13725b2f", "before": "df479f79c157efbf871df599ae2eaf159bf9f3ed"}, "public": true, "created_at": "2026-04-04T19:42:36Z"}, {"id": "10195669407", "type": "PushEvent", "actor": {"id": 215815473, "login": "ALPHA-STUDIO-CODE", "display_login": "ALPHA-STUDIO-CODE", "gravatar_id": "", "url": "https://api.github.com/users/ALPHA-STUDIO-CODE", "avatar_url": "https://avatars.githubusercontent.com/u/215815473?", "location": "Where I can learn and develop."}, "repo": {"id": 1198816250, "name": "ALPHA-STUDIO-CODE/CSS", "url": "https://api.github.com/repos/ALPHA-STUDIO-CODE/CSS"}, "payload": {"repository_id": 1198816250, "push_id": 32488771573, "ref": "refs/heads/main", "head": "f1f0d78aba89e2af4dc096329f933b6588c9e7dd", "before": "d69570c489b7478aa9f04623e81d9ebec6378bf8"}, "public": true, "created_at": "2026-04-04T19:42:36Z"}, {"id": "10195669412", "type": "PushEvent", "actor": {"id": 96393042, "login": "KEOZ5", "display_login": "KEOZ5", "gravatar_id": "", "url": "https://api.github.com/users/KEOZ5", "avatar_url": "https://avatars.githubusercontent.com/u/96393042?", "location": "Not Specified"}, "repo": {"id": 1200515924, "name": "KEOZ5/proxora-agent", "url": "https://api.github.com/repos/KEOZ5/proxora-agent"}, "payload": {"repository_id": 1200515924, "push_id": 32488771581, "ref": "refs/heads/main", "head": "0ab0d0753748c4fea7957f655199767eba7537d5", "before": "d139e180ccfd21a153fd28b6049d35e02fcfba3d"}, "public": true, "created_at": "2026-04-04T19:42:36Z"}, {"id": "10195669414", "type": "PushEvent", "actor": {"id": 95378285, "login": "Kholdy776", "display_login": "Kholdy776", "gravatar_id": "", "url": "https://api.github.com/users/Kholdy776", "avatar_url": "https://avatars.githubusercontent.com/u/95378285?", "location": "Not Specified"}, "repo": {"id": 665317423, "name": "Kholdy776/eo3balanceskillsim", "url": "https://api.github.com/repos/Kholdy776/eo3balanceskillsim"}, "payload": {"repository_id": 665317423, "push_id": 32488771590, "ref": "refs/heads/main", "head": "8e90c521bc3888f5075872f718ef33f3d42bc875", "before": "51bb8067c95c8472ec907a17fe8f59b35b7203ec"}, "public": true, "created_at": "2026-04-04T19:42:36Z"}, {"id": "10195669415", "type": "PushEvent", "actor": {"id": 47603275, "login": "NezbednikSK", "display_login": "NezbednikSK", "gravatar_id": "", "url": "https://api.github.com/users/NezbednikSK", "avatar_url": "https://avatars.githubusercontent.com/u/47603275?", "location": "Slovakia"}, "repo": {"id": 1201515001, "name": "siloh-gh/T-20260404-192", "url": "https://api.github.com/repos/siloh-gh/T-20260404-192"}, "payload": {"repository_id": 1201515001, "push_id": 32488771585, "ref": "refs/heads/main", "head": "07d9f17b541c1b981ca4460fc4a0077fee6266e1", "before": "0646023ebb94a023b7f30742bf3500f9f250b541"}, "public": true, "created_at": "2026-04-04T19:42:36Z", "org": {"id": 242863882, "login": "siloh-gh", "gravatar_id": "", "url": "https://api.github.com/orgs/siloh-gh", "avatar_url": "https://avatars.githubusercontent.com/u/242863882?"}}, {"id": "10195669416", "type": "PushEvent", "actor": {"id": 209770019, "login": "noorayemm", "display_login": "noorayemm", "gravatar_id": "", "url": "https://api.github.com/users/noorayemm", "avatar_url": "https://avatars.githubusercontent.com/u/209770019?", "location": "Not Specified"}, "repo": {"id": 1201458575, "name": "noorayemm/my-client-demo-site", "url": "https://api.github.com/repos/noorayemm/my-client-demo-site"}, "payload": {"repository_id": 1201458575, "push_id": 32488769559, "ref": "refs/heads/main", "head": "618a59b0e1e3209d3d857bd8f023a59ce6be53a0", "before": "7d93b9aa4f27dda6ff20713644c6c332bf8be428"}, "public": true, "created_at": "2026-04-04T19:42:29Z"}, {"id": "10195669418", "type": "PushEvent", "actor": {"id": 50833808, "login": "KleinGrrmpf", "display_login": "KleinGrrmpf", "gravatar_id": "", "url": "https://api.github.com/users/KleinGrrmpf", "avatar_url": "https://avatars.githubusercontent.com/u/50833808?", "location": "Not Specified"}, "repo": {"id": 1196501868, "name": "KleinGrrmpf/GT5-Unofficial", "url": "https://api.github.com/repos/KleinGrrmpf/GT5-Unofficial"}, "payload": {"repository_id": 1196501868, "push_id": 32488771594, "ref": "refs/heads/KleinGrrmpf/wireless-machine-controller-cover", "head": "b120abe3e34056a55a9e85c81ba6d296657d7576", "before": "b087bdc125599fd2ae77f1ae23db49588b223f78"}, "public": true, "created_at": "2026-04-04T19:42:36Z"}, {"id": "10195669419", "type": "CreateEvent", "actor": {"id": 268815215, "login": "aazrdev", "display_login": "aazrdev", "gravatar_id": "", "url": "https://api.github.com/users/aazrdev", "avatar_url": "https://avatars.githubusercontent.com/u/268815215?", "location": "Santiago, Chile"}, "repo": {"id": 1201522149, "name": "aazrdev/EntreSolyCemento", "url": "https://api.github.com/repos/aazrdev/EntreSolyCemento"}, "payload": {"ref": "main", "ref_type": "branch", "full_ref": "refs/heads/main", "master_branch": "main", "description": null, "pusher_type": "user"}, "public": true, "created_at": "2026-04-04T19:42:36Z"}, {"id": "10195669421", "type": "PushEvent", "actor": {"id": 247285850, "login": "samabrllan-arch", "display_login": "samabrllan-arch", "gravatar_id": "", "url": "https://api.github.com/users/samabrllan-arch", "avatar_url": "https://avatars.githubusercontent.com/u/247285850?", "location": "Not Specified"}, "repo": {"id": 1200167925, "name": "samabrllan-arch/chayo-cliente", "url": "https://api.github.com/repos/samabrllan-arch/chayo-cliente"}, "payload": {"repository_id": 1200167925, "push_id": 32488771587, "ref": "refs/heads/main", "head": "02d519c5234bfc982516b03aab0c65d4edd754be", "before": "407718f5c87f91dbc0ed6aeb25b13105494fc966"}, "public": true, "created_at": "2026-04-04T19:42:36Z"}, {"id": "10195669422", "type": "PushEvent", "actor": {"id": 10308233, "login": "Szer", "display_login": "Szer", "gravatar_id": "", "url": "https://api.github.com/users/Szer", "avatar_url": "https://avatars.githubusercontent.com/u/10308233?", "location": "Dublin, Ireland"}, "repo": {"id": 696730834, "name": "fsharplang-ru/vahter-bot", "url": "https://api.github.com/repos/fsharplang-ru/vahter-bot"}, "payload": {"repository_id": 696730834, "push_id": 32488771574, "ref": "refs/heads/main", "head": "ce8bb3da3573109ac3cfc074553d4e1dee46cf27", "before": "16e2878c3095533033929c0ea7186887f1a1e09b"}, "public": true, "created_at": "2026-04-04T19:42:36Z", "org": {"id": 27734179, "login": "fsharplang-ru", "gravatar_id": "", "url": "https://api.github.com/orgs/fsharplang-ru", "avatar_url": "https://avatars.githubusercontent.com/u/27734179?"}}, {"id": "10195669423", "type": "PushEvent", "actor": {"id": 260032333, "login": "skstmdals1-ctrl", "display_login": "skstmdals1-ctrl", "gravatar_id": "", "url": "https://api.github.com/users/skstmdals1-ctrl", "avatar_url": "https://avatars.githubusercontent.com/u/260032333?", "location": "Not Specified"}, "repo": {"id": 1198557675, "name": "skstmdals1-ctrl/bybit-dashboard-client1", "url": "https://api.github.com/repos/skstmdals1-ctrl/bybit-dashboard-client1"}, "payload": {"repository_id": 1198557675, "push_id": 32488771589, "ref": "refs/heads/main", "head": "ecd68ecbe3ed75adf9392992f374da31ed339048", "before": "6dc01d67c537fea43dcbe6ac9b55698954d1fdad"}, "public": true, "created_at": "2026-04-04T19:42:36Z"}, {"id": "10195669494", "type": "PushEvent", "actor": {"id": 271832708, "login": "thomv-flow8", "display_login": "thomv-flow8", "gravatar_id": "", "url": "https://api.github.com/users/thomv-flow8", "avatar_url": "https://avatars.githubusercontent.com/u/271832708?", "location": "Not Specified"}, "repo": {"id": 1195392735, "name": "thomv-flow8/Flow-8", "url": "https://api.github.com/repos/thomv-flow8/Flow-8"}, "payload": {"repository_id": 1195392735, "push_id": 32488771641, "ref": "refs/heads/main", "head": "69ecc6982324a5729d9d81f0216fc862116f8f10", "before": "a42c75378005a02b9f91974b5bf2cda889cca23d"}, "public": true, "created_at": "2026-04-04T19:42:36Z"}, {"id": "10195669373", "type": "PushEvent", "actor": {"id": 41898282, "login": "github-actions[bot]", "display_login": "github-actions", "gravatar_id": "", "url": "https://api.github.com/users/github-actions[bot]", "avatar_url": "https://avatars.githubusercontent.com/u/41898282?", "location": "Not Specified"}, "repo": {"id": 1146111540, "name": "vannifr/ai-project-blueprint", "url": "https://api.github.com/repos/vannifr/ai-project-blueprint"}, "payload": {"repository_id": 1146111540, "push_id": 32488771532, "ref": "refs/heads/main", "head": "4b47566206f4488edc15806e9c0b42af18eeb1d7", "before": "921f2daf848807be124d7c3161e5a249f6d7f9a0"}, "public": true, "created_at": "2026-04-04T19:42:36Z"}, {"id": "10195669432", "type": "PushEvent", "actor": {"id": 271929950, "login": "jenniphillips79", "display_login": "jenniphillips79", "gravatar_id": "", "url": "https://api.github.com/users/jenniphillips79", "avatar_url": "https://avatars.githubusercontent.com/u/271929950?", "location": "Not Specified"}, "repo": {"id": 1195141802, "name": "jenniphillips79/tumblr-stats-data", "url": "https://api.github.com/repos/jenniphillips79/tumblr-stats-data"}, "payload": {"repository_id": 1195141802, "push_id": 32488771873, "ref": "refs/heads/main", "head": "6ba368b082e19ad0f08ba70afac8ac59dd79e407", "before": "7d19685a4b9ebcb2f8044cdd4e39acd2b6ffc212"}, "public": true, "created_at": "2026-04-04T19:42:37Z"}, {"id": "10195669504", "type": "PushEvent", "actor": {"id": 30376729, "login": "schalkms", "display_login": "schalkms", "gravatar_id": "", "url": "https://api.github.com/users/schalkms", "avatar_url": "https://avatars.githubusercontent.com/u/30376729?", "location": "Austria"}, "repo": {"id": 71729669, "name": "detekt/detekt", "url": "https://api.github.com/repos/detekt/detekt"}, "payload": {"repository_id": 71729669, "push_id": 32488771666, "ref": "refs/heads/main", "head": "cb890b29bd108f699de9b81f6c65ac2cc300de96", "before": "2cf27c4553a8730c458771382e35312d6163facd"}, "public": true, "created_at": "2026-04-04T19:42:36Z", "org": {"id": 57960713, "login": "detekt", "gravatar_id": "", "url": "https://api.github.com/orgs/detekt", "avatar_url": "https://avatars.githubusercontent.com/u/57960713?"}}, {"id": "10195669479", "type": "PushEvent", "actor": {"id": 109068167, "login": "Fl9999", "display_login": "Fl9999", "gravatar_id": "", "url": "https://api.github.com/users/Fl9999", "avatar_url": "https://avatars.githubusercontent.com/u/109068167?", "location": "Not Specified"}, "repo": {"id": 512677672, "name": "Fl9999/fl9999.github.io", "url": "https://api.github.com/repos/Fl9999/fl9999.github.io"}, "payload": {"repository_id": 512677672, "push_id": 32488771630, "ref": "refs/heads/master", "head": "708f1bb4650d144e18d07fc4ef85fe8ee42eda4f", "before": "3ddc1006aabdf577e86810c1e695d0d79bc92d40"}, "public": true, "created_at": "2026-04-04T19:42:36Z"}, {"id": "10195669442", "type": "PushEvent", "actor": {"id": 41898282, "login": "github-actions[bot]", "display_login": "github-actions", "gravatar_id": "", "url": "https://api.github.com/users/github-actions[bot]", "avatar_url": "https://avatars.githubusercontent.com/u/41898282?", "location": "Not Specified"}, "repo": {"id": 1118316045, "name": "averageface-em/daily_leclerc_widget", "url": "https://api.github.com/repos/averageface-em/daily_leclerc_widget"}, "payload": {"repository_id": 1118316045, "push_id": 32488771620, "ref": "refs/heads/main", "head": "30b7deb696e66ae9c64642283952d6bb5e8ce260", "before": "80a467c9b75e5887eb8cc1a93f06c7e6532075f2"}, "public": true, "created_at": "2026-04-04T19:42:36Z"}, {"id": "10195669444", "type": "PushEvent", "actor": {"id": 41898282, "login": "github-actions[bot]", "display_login": "github-actions", "gravatar_id": "", "url": "https://api.github.com/users/github-actions[bot]", "avatar_url": "https://avatars.githubusercontent.com/u/41898282?", "location": "Not Specified"}, "repo": {"id": 832827081, "name": "Ezjfc/Ezjfc", "url": "https://api.github.com/repos/Ezjfc/Ezjfc"}, "payload": {"repository_id": 832827081, "push_id": 32488771613, "ref": "refs/heads/main", "head": "a56e49bf6708dbffd18aab7e05e1b70738c96dc0", "before": "b02f31bb78889f9f71db23af00ae55329f8f37b8"}, "public": true, "created_at": "2026-04-04T19:42:36Z"}, {"id": "10195669445", "type": "CreateEvent", "actor": {"id": 41898282, "login": "github-actions[bot]", "display_login": "github-actions", "gravatar_id": "", "url": "https://api.github.com/users/github-actions[bot]", "avatar_url": "https://avatars.githubusercontent.com/u/41898282?", "location": "Not Specified"}, "repo": {"id": 1165240453, "name": "FatecNeoHorizon/API_6S", "url": "https://api.github.com/repos/FatecNeoHorizon/API_6S"}, "payload": {"ref": "bugfix/60-fix-filter-logic-for-dec-and-fec-endpoints-by-period", "ref_type": "branch", "full_ref": "refs/heads/bugfix/60-fix-filter-logic-for-dec-and-fec-endpoints-by-period", "master_branch": "main", "description": "Repositório destinado a projeto de API do sexto semestre do curso de banco de dados - Fatec São José dos Campos.", "pusher_type": "user"}, "public": true, "created_at": "2026-04-04T19:42:36Z", "org": {"id": 231145799, "login": "FatecNeoHorizon", "gravatar_id": "", "url": "https://api.github.com/orgs/FatecNeoHorizon", "avatar_url": "https://avatars.githubusercontent.com/u/231145799?"}}, {"id": "10195669454", "type": "PushEvent", "actor": {"id": 262197254, "login": "Samuel-McC", "display_login": "Samuel-McC", "gravatar_id": "", "url": "https://api.github.com/users/Samuel-McC", "avatar_url": "https://avatars.githubusercontent.com/u/262197254?", "location": "Not Specified"}, "repo": {"id": 1162689384, "name": "Samuel-McC/supply-program-engine", "url": "https://api.github.com/repos/Samuel-McC/supply-program-engine"}, "payload": {"repository_id": 1162689384, "push_id": 32488771609, "ref": "refs/heads/main", "head": "66eaf9f7d9b2837ef32756481c5a1cd3f1999069", "before": "ab930b2aa13d3b79dd8b9bf24e1373b171010c24"}, "public": true, "created_at": "2026-04-04T19:42:36Z"}, {"id": "10195669463", "type": "DeleteEvent", "actor": {"id": 192753212, "login": "yorha-operator-6o[bot]", "display_login": "yorha-operator-6o", "gravatar_id": "", "url": "https://api.github.com/users/yorha-operator-6o[bot]", "avatar_url": "https://avatars.githubusercontent.com/u/192753212?", "location": "Not Specified"}, "repo": {"id": 908042874, "name": "shikanime-studio/actions", "url": "https://api.github.com/repos/shikanime-studio/actions"}, "payload": {"ref": "gh/shikanime/4/orig", "ref_type": "branch", "full_ref": "refs/heads/gh/shikanime/4/orig", "pusher_type": "user"}, "public": true, "created_at": "2026-04-04T19:42:36Z", "org": {"id": 106672417, "login": "shikanime-studio", "gravatar_id": "", "url": "https://api.github.com/orgs/shikanime-studio", "avatar_url": "https://avatars.githubusercontent.com/u/106672417?"}}]